xdof_sdk/README.md
xdof_sdk/__init__.py
xdof_sdk/data/__init__.py
xdof_sdk/data/constants.py
xdof_sdk/data/fk.py
xdof_sdk/data/trajectory.py
xdof_sdk/data/xmi_helper.py
xdof_sdk/data/models/panda.xml
xdof_sdk/data/models/yam.xml
xdof_sdk/data/schema/__init__.py
xdof_sdk/data/schema/annotations.py
xdof_sdk/data/schema/camera_info.py
xdof_sdk/data/schema/keys.py
xdof_sdk/data/schema/metadata.py
xdof_sdk/data/schema/station_metadata.py
xdof_sdk/data/schema/types.py
xdof_sdk/data/schema/proto/robot.proto
xdof_sdk/data/schema/proto/robot_pb2.py
xdof_sdk/data/schema/proto/task.proto
xdof_sdk/data/schema/proto/task_pb2.py
xdof_sdk/data/schema/tests/test_camera_schema.py
xdof_sdk/data/schema/tests/test_station_metadata.py
xdof_sdk/data/schema/tests/test_trajectory.py
xdof_sdk/data/schema/tests/test_transform3d.py
xdof_sdk/data/schema/tests/test_types.py
xdof_sdk/data/schema/tests/trajectory_test_util.py
xdof_sdk/viz/__init__.py
xdof_sdk/viz/name_map.py
xdof_sdk/viz/visualizer.py
xdof_sdk-0.0.1rc5.dist-info/METADATA
xdof_sdk-0.0.1rc5.dist-info/WHEEL
xdof_sdk-0.0.1rc5.dist-info/entry_points.txt
xdof_sdk-0.0.1rc5.dist-info/RECORD
